setup.py
sunnyday_bg3737366/__init__.py
sunnyday_bg3737366/sunnyday.py
sunnyday_bg3737366.egg-info/PKG-INFO
sunnyday_bg3737366.egg-info/SOURCES.txt
sunnyday_bg3737366.egg-info/dependency_links.txt
sunnyday_bg3737366.egg-info/requires.txt
sunnyday_bg3737366.egg-info/top_level.txt